pyfsviz-0.2.4.dist-info/METADATA
pyfsviz-0.2.4.dist-info/WHEEL
pyfsviz-0.2.4.dist-info/entry_points.txt
pyfsviz-0.2.4.dist-info/licenses/LICENSE
pyfsviz/__init__.py
pyfsviz/__main__.py
pyfsviz/_internal/__init__.py
pyfsviz/_internal/cli.py
pyfsviz/_internal/debug.py
pyfsviz/_internal/html/group.html
pyfsviz/_internal/html/individual.html
pyfsviz/_internal/mni305.cor.mgz
pyfsviz/_internal/mni305.cor.nii.gz
pyfsviz/freesurfer.py
pyfsviz/py.typed
pyfsviz/reports.py
pyfsviz/stats.py
pyfsviz-0.2.4.dist-info/RECORD
